Metadata-Version: 2.1
Name: estuary-airbyte-cdk
Version: 0.1.56
Summary: A framework for writing Airbyte Connectors. Estuary's fork.
Home-page: https://github.com/estuary/airbyte
Author: Estuary
Author-email: help@estuary.dev
License: MIT
Project-URL: Documentation, https://docs.airbyte.io/
Project-URL: Source, https://github.com/airbytehq/airbyte
Project-URL: Tracker, https://github.com/airbytehq/airbyte/issues
Keywords: airbyte connector-development-kit cdk
Classifier: Development Status :: 3 - Alpha
Classifier: Intended Audience :: Developers
Classifier: Topic :: Scientific/Engineering
Classifier: Topic :: Software Development :: Libraries :: Python Modules
Classifier: License :: OSI Approved :: MIT License
Classifier: Programming Language :: Python :: 3.9
Requires-Python: >=3.9
License-File: LICENSE.txt
Requires-Dist: backoff
Requires-Dist: dpath (~=2.0.1)
Requires-Dist: jsonschema (~=3.2.0)
Requires-Dist: jsonref (~=0.2)
Requires-Dist: pendulum
Requires-Dist: pydantic (~=1.6)
Requires-Dist: PyYAML (~=5.4)
Requires-Dist: requests
Requires-Dist: sentry-sdk (~=1.5.1)
Requires-Dist: vcrpy
Requires-Dist: Deprecated (~=1.2)
Provides-Extra: dev
Requires-Dist: MyPy (~=0.812) ; extra == 'dev'
Requires-Dist: pytest ; extra == 'dev'
Requires-Dist: pytest-cov ; extra == 'dev'
Requires-Dist: pytest-mock ; extra == 'dev'
Requires-Dist: requests-mock ; extra == 'dev'
Requires-Dist: pytest-httpserver ; extra == 'dev'
Provides-Extra: sphinx-docs
Requires-Dist: Sphinx (~=4.2) ; extra == 'sphinx-docs'
Requires-Dist: sphinx-rtd-theme (~=1.0) ; extra == 'sphinx-docs'
